src/__init__.py
src/main.py
src/static/style.css
src/static/web-background.png
src/templates/client_data.html
src/templates/index.html
src/templates/select_countries.html
tests/__init__.py
tests/test_main.py
RATS_PRO_4abn-1.15.0.dist-info/METADATA
RATS_PRO_4abn-1.15.0.dist-info/WHEEL
RATS_PRO_4abn-1.15.0.dist-info/top_level.txt
RATS_PRO_4abn-1.15.0.dist-info/RECORD
